babelfish/__init__.py
babelfish/country.py
babelfish/exceptions.py
babelfish/language.py
babelfish/script.py
babelfish/tests.py
babelfish/converters/__init__.py
babelfish/converters/alpha2.py
babelfish/converters/alpha3b.py
babelfish/converters/alpha3t.py
babelfish/converters/countryname.py
babelfish/converters/name.py
babelfish/converters/opensubtitles.py
babelfish/converters/scope.py
babelfish/converters/type.py
babelfish/data/iso-3166-1.txt
babelfish/data/iso-639-3.tab
babelfish/data/iso15924-utf8-20131012.txt
babelfish/data/opensubtitles_languages.txt
temp_babelfish-0.5.6.dev0.dist-info/AUTHORS
temp_babelfish-0.5.6.dev0.dist-info/LICENSE
temp_babelfish-0.5.6.dev0.dist-info/METADATA
temp_babelfish-0.5.6.dev0.dist-info/WHEEL
temp_babelfish-0.5.6.dev0.dist-info/top_level.txt
temp_babelfish-0.5.6.dev0.dist-info/RECORD
